gython/__init__.py
gython/__main__.py
gython/_version.py
gython/ast_utils.py
gython/code_writer.py
gython/gython.py
gython/gython_to_coffee.py
gython/gython_to_dart.py
gython/gython_to_go.py
gython/gython_to_lua.py
gython/gython_to_luajs.py
gython/inline_function.py
gython/ministdlib.py
gython/python_to_gython.py
gython/python_to_visjs.py
gython/translator.py
gython/typedpython.py
gython-0.9.9.dist-info/DESCRIPTION.rst
gython-0.9.9.dist-info/METADATA
gython-0.9.9.dist-info/RECORD
gython-0.9.9.dist-info/WHEEL
gython-0.9.9.dist-info/entry_points.txt
gython-0.9.9.dist-info/metadata.json
gython-0.9.9.dist-info/top_level.txt
