Metadata-Version: 2.0
Name: gython
Version: 0.9.9
Summary: Python to go transpiler
Home-page: https://github.com/xoviat/gython
Author: Mars Galactic
Author-email: xoviat@users.noreply.github.com
License: ### GNU GENERAL PUBLIC LICENSE
Platform: any
